README.md
setup.py
bin/FancyChat.py
fancychat/Editor.py
fancychat/MsgArrive.py
fancychat/MsgSend.py
fancychat/ScrollView.py
fancychat/TitleBar.py
fancychat/__init__.py
fancychat.egg-info/PKG-INFO
fancychat.egg-info/SOURCES.txt
fancychat.egg-info/dependency_links.txt
fancychat.egg-info/requires.txt
fancychat.egg-info/top_level.txt
share/fancychat/appbar.close.svg
share/fancychat/appbar.control.fastforward.variant.svg
share/fancychat/appbar.lines.horizontal.4.svg
share/fancychat/fbmessenger.svg
share/fancychat/kphotoalbum.svg
share/fancychat/msg-text-arrive.svg
share/fancychat/msg-text-send.svg
share/fancychat/preferences-desktop-emoticons.svg
share/fancychat/preferences-desktop-emoticons2.svg
share/fancychat/styles.css