Metadata-Version: 1.0
Name: fancychat
Version: 1.1.5
Summary: fancy chat example
Home-page: https://github.com/joseluis8906/fancychat
Author: joseluis
Author-email: joseluiscacere8906@gmail.com
License: MIT
Platform: UNKNOWN
